swiftrank/__init__.py
swiftrank/interface/__init__.py
swiftrank/interface/api.py
swiftrank/interface/cli.py
swiftrank/interface/utils.py
swiftrank/ranker.py
swiftrank/settings.py
swiftrank-1.3.0.dist-info/entry_points.txt
swiftrank-1.3.0.dist-info/LICENSE
swiftrank-1.3.0.dist-info/METADATA
swiftrank-1.3.0.dist-info/WHEEL
swiftrank-1.3.0.dist-info/RECORD
