Metadata-Version: 2.1
Name: swiftrank
Version: 1.3.0
Summary: Compact, ultra-fast SoTA reranker enhancing retrieval pipelines and terminal applications.
License: Apache Software License (Apache 2.0)
Author: Harsh Verma
Author-email: synacktra.work@gmail.com
Requires-Python: >=3.8,<4.0
Classifier: License :: Other/Proprietary License
Classifier: Programming Language :: Python :: 3
Classifier: Programming Language :: Python :: 3.8
Classifier: Programming Language :: Python :: 3.9
Classifier: Programming Language :: Python :: 3.10
Classifier: Programming Language :: Python :: 3.11
Classifier: Programming Language :: Python :: 3.12
Requires-Dist: cyclopts (==2.1.2)
Requires-Dist: fastapi (==0.110.1)
Requires-Dist: numpy (>=1.24.4)
Requires-Dist: onnxruntime (==1.16.3)
Requires-Dist: orjson (==3.9.10)
Requires-Dist: pydantic (==2.6.4)
Requires-Dist: pyyaml (==6.0.1)
Requires-Dist: requests (==2.31.0)
Requires-Dist: rich (==13.7.0)
Requires-Dist: tokenizers (>=0.15.0,<0.16.0)
Requires-Dist: tqdm (==4.66.1)
Requires-Dist: uvicorn (==0.29.0)
